CustomGroqChat/__init__.py
CustomGroqChat/api_client.py
CustomGroqChat/config_loader.py
CustomGroqChat/exceptions.py
CustomGroqChat/groq_client.py
CustomGroqChat/queue_manager.py
CustomGroqChat/rate_limit_handler.py
CustomGroqChat/request_handler.py
CustomGroqChat/token_counter.py
customgroqchat-0.1.0.dist-info/licenses/LICENSE
customgroqchat-0.1.0.dist-info/METADATA
customgroqchat-0.1.0.dist-info/WHEEL
customgroqchat-0.1.0.dist-info/top_level.txt
customgroqchat-0.1.0.dist-info/RECORD
