Metadata-Version: 2.4
Name: customgroqchat
Version: 0.1.0
Summary: Python client for the Groq Cloud API with intelligent rate limiting
Home-page: https://github.com/Arslanex/CustomGroqChat
Author: Enes Arslan
Author-email: enes@vidinsight.com.tr
License: MIT
Project-URL: Documentation, https://github.com/Arslanex/CustomGroqChat/docs
Project-URL: Source, https://github.com/Arslanex/CustomGroqChat
Project-URL: Issue Tracker, https://github.com/Arslanex/CustomGroqChat/issues
Keywords: groq,api,nlp,ai,language model,rate limiting,queue
Classifier: Programming Language :: Python :: 3
Classifier: Programming Language :: Python :: 3.8
Classifier: Programming Language :: Python :: 3.9
Classifier: Programming Language :: Python :: 3.10
Classifier: License :: OSI Approved :: MIT License
Classifier: Operating System :: OS Independent
Classifier: Topic :: Software Development :: Libraries :: Python Modules
Classifier: Topic :: Scientific/Engineering :: Artificial Intelligence
Requires-Python: >=3.8
License-File: LICENSE
Requires-Dist: aiohttp>=3.8.0
Requires-Dist: tiktoken>=0.4.0
Requires-Dist: asyncio>=3.4.3
Dynamic: author
Dynamic: author-email
Dynamic: classifier
Dynamic: description
Dynamic: description-content-type
Dynamic: home-page
Dynamic: keywords
Dynamic: license-file
Dynamic: project-url
Dynamic: requires-dist
Dynamic: requires-python
Dynamic: summary
